{
  "manifestVersion": "3.2",
  "proxies": [
    {
      "address": "0xC0725e1FaEA28e42EA7678Da8326382A29007a60",
      "txHash": "0xce351f7620fefce37063b4c0348995265b23fefac9989dbb0ed887528f21cd4e",
      "kind": "uups"
    },
    {
      "address": "0x1051bc3b5b9C5C66574C88c54B2a2E0bCa79C567",
      "kind": "uups"
    },
    {
      "address": "0xAb2B61C03A5c6c6b9CC4810F80b29ae14D75256F",
      "kind": "uups"
    }
  ],
  "impls": {
    "79f7564c4965283ec2910876207f98222586527c89093735fb6ea3d81a9cc387": {
      "address": "0xcD6FD8284B4916288d238D059b4C9F54228abd6a",
      "txHash": "0x315c0867eb4d6ea026ef4103fa6c520a8e95cba93d49071b4224c57d911a32de",
      "layout": {
        "solcVersion": "0.8.9",
        "storage": [
          {
            "label": "_initialized",
            "offset": 0,
            "slot": "0",
            "type": "t_uint8",
            "contract": "Initializable",
            "src": "@openzeppelin/contracts-upgradeable/proxy/utils/Initializable.sol:62",
            "retypedFrom": "bool"
          },
          {
            "label": "_initializing",
            "offset": 1,
            "slot": "0",
            "type": "t_bool",
            "contract": "Initializable",
            "src": "@openzeppelin/contracts-upgradeable/proxy/utils/Initializable.sol:67"
          },
          {
            "label": "__gap",
            "offset": 0,
            "slot": "1",
            "type": "t_array(t_uint256)50_storage",
            "contract": "ContextUpgradeable",
            "src": "@openzeppelin/contracts-upgradeable/utils/ContextUpgradeable.sol:36"
          },
          {
            "label": "_owner",
            "offset": 0,
            "slot": "51",
            "type": "t_address",
            "contract": "OwnableUpgradeable",
            "src": "@openzeppelin/contracts-upgradeable/access/OwnableUpgradeable.sol:22"
          },
          {
            "label": "__gap",
            "offset": 0,
            "slot": "52",
            "type": "t_array(t_uint256)49_storage",
            "contract": "OwnableUpgradeable",
            "src": "@openzeppelin/contracts-upgradeable/access/OwnableUpgradeable.sol:94"
          },
          {
            "label": "_status",
            "offset": 0,
            "slot": "101",
            "type": "t_uint256",
            "contract": "ReentrancyGuardUpgradeable",
            "src": "@openzeppelin/contracts-upgradeable/security/ReentrancyGuardUpgradeable.sol:38"
          },
          {
            "label": "__gap",
            "offset": 0,
            "slot": "102",
            "type": "t_array(t_uint256)49_storage",
            "contract": "ReentrancyGuardUpgradeable",
            "src": "@openzeppelin/contracts-upgradeable/security/ReentrancyGuardUpgradeable.sol:80"
          },
          {
            "label": "__gap",
            "offset": 0,
            "slot": "151",
            "type": "t_array(t_uint256)50_storage",
            "contract": "ERC1967UpgradeUpgradeable",
            "src": "@openzeppelin/contracts-upgradeable/proxy/ERC1967/ERC1967UpgradeUpgradeable.sol:211"
          },
          {
            "label": "__gap",
            "offset": 0,
            "slot": "201",
            "type": "t_array(t_uint256)50_storage",
            "contract": "UUPSUpgradeable",
            "src": "@openzeppelin/contracts-upgradeable/proxy/utils/UUPSUpgradeable.sol:107"
          },
          {
            "label": "token",
            "offset": 0,
            "slot": "251",
            "type": "t_contract(IERC20)2402",
            "contract": "DeciblingFaucet",
            "src": "contracts/DeciblingFaucet.sol:22"
          },
          {
            "label": "faucets",
            "offset": 0,
            "slot": "252",
            "type": "t_mapping(t_address,t_uint256)",
            "contract": "DeciblingFaucet",
            "src": "contracts/DeciblingFaucet.sol:24"
          }
        ],
        "types": {
          "t_address": {
            "label": "address",
            "numberOfBytes": "20"
          },
          "t_array(t_uint256)49_storage": {
            "label": "uint256[49]",
            "numberOfBytes": "1568"
          },
          "t_array(t_uint256)50_storage": {
            "label": "uint256[50]",
            "numberOfBytes": "1600"
          },
          "t_bool": {
            "label": "bool",
            "numberOfBytes": "1"
          },
          "t_contract(IERC20)2402": {
            "label": "contract IERC20",
            "numberOfBytes": "20"
          },
          "t_mapping(t_address,t_uint256)": {
            "label": "mapping(address => uint256)",
            "numberOfBytes": "32"
          },
          "t_uint256": {
            "label": "uint256",
            "numberOfBytes": "32"
          },
          "t_uint8": {
            "label": "uint8",
            "numberOfBytes": "1"
          }
        }
      }
    },
    "876116c5e4d85a03bdb7e9d0338d2b52a450c26adaa1ae710a77089e002786b0": {
      "address": "0x7654f29D42a599Da66FcbC55E497C251167Aa44f",
      "layout": {
        "solcVersion": "0.8.9",
        "storage": [
          {
            "label": "_initialized",
            "offset": 0,
            "slot": "0",
            "type": "t_uint8",
            "contract": "Initializable",
            "src": "@openzeppelin/contracts-upgradeable/proxy/utils/Initializable.sol:62",
            "retypedFrom": "bool"
          },
          {
            "label": "_initializing",
            "offset": 1,
            "slot": "0",
            "type": "t_bool",
            "contract": "Initializable",
            "src": "@openzeppelin/contracts-upgradeable/proxy/utils/Initializable.sol:67"
          },
          {
            "label": "_status",
            "offset": 0,
            "slot": "1",
            "type": "t_uint256",
            "contract": "ReentrancyGuardUpgradeable",
            "src": "@openzeppelin/contracts-upgradeable/security/ReentrancyGuardUpgradeable.sol:38"
          },
          {
            "label": "__gap",
            "offset": 0,
            "slot": "2",
            "type": "t_array(t_uint256)49_storage",
            "contract": "ReentrancyGuardUpgradeable",
            "src": "@openzeppelin/contracts-upgradeable/security/ReentrancyGuardUpgradeable.sol:80"
          },
          {
            "label": "__gap",
            "offset": 0,
            "slot": "51",
            "type": "t_array(t_uint256)50_storage",
            "contract": "ContextUpgradeable",
            "src": "@openzeppelin/contracts-upgradeable/utils/ContextUpgradeable.sol:36"
          },
          {
            "label": "_owner",
            "offset": 0,
            "slot": "101",
            "type": "t_address",
            "contract": "OwnableUpgradeable",
            "src": "@openzeppelin/contracts-upgradeable/access/OwnableUpgradeable.sol:22"
          },
          {
            "label": "__gap",
            "offset": 0,
            "slot": "102",
            "type": "t_array(t_uint256)49_storage",
            "contract": "OwnableUpgradeable",
            "src": "@openzeppelin/contracts-upgradeable/access/OwnableUpgradeable.sol:94"
          },
          {
            "label": "__gap",
            "offset": 0,
            "slot": "151",
            "type": "t_array(t_uint256)50_storage",
            "contract": "ERC1967UpgradeUpgradeable",
            "src": "@openzeppelin/contracts-upgradeable/proxy/ERC1967/ERC1967UpgradeUpgradeable.sol:197"
          },
          {
            "label": "__gap",
            "offset": 0,
            "slot": "201",
            "type": "t_array(t_uint256)50_storage",
            "contract": "UUPSUpgradeable",
            "src": "@openzeppelin/contracts-upgradeable/proxy/utils/UUPSUpgradeable.sol:107"
          },
          {
            "label": "token",
            "offset": 0,
            "slot": "251",
            "type": "t_contract(IERC20)4886",
            "contract": "DeciblingAuctionV2",
            "src": "contracts/DeciblingAuctionV2.sol:18"
          },
          {
            "label": "nftContract",
            "offset": 0,
            "slot": "252",
            "type": "t_contract(DeciblingNFTV2)7549",
            "contract": "DeciblingAuctionV2",
            "src": "contracts/DeciblingAuctionV2.sol:19"
          },
          {
            "label": "firstSaleFee",
            "offset": 0,
            "slot": "253",
            "type": "t_uint256",
            "contract": "DeciblingAuctionV2",
            "src": "contracts/DeciblingAuctionV2.sol:22"
          },
          {
            "label": "secondSaleFee",
            "offset": 0,
            "slot": "254",
            "type": "t_uint256",
            "contract": "DeciblingAuctionV2",
            "src": "contracts/DeciblingAuctionV2.sol:23"
          },
          {
            "label": "platformFeeRecipient",
            "offset": 0,
            "slot": "255",
            "type": "t_address",
            "contract": "DeciblingAuctionV2",
            "src": "contracts/DeciblingAuctionV2.sol:25"
          },
          {
            "label": "nftAuctionInfos",
            "offset": 0,
            "slot": "256",
            "type": "t_mapping(t_uint256,t_struct(NftAuctionInfo)6202_storage)",
            "contract": "DeciblingAuctionV2",
            "src": "contracts/DeciblingAuctionV2.sol:47"
          },
          {
            "label": "auctions",
            "offset": 0,
            "slot": "257",
            "type": "t_mapping(t_uint256,t_struct(Auction)6195_storage)",
            "contract": "DeciblingAuctionV2",
            "src": "contracts/DeciblingAuctionV2.sol:48"
          },
          {
            "label": "topBids",
            "offset": 0,
            "slot": "258",
            "type": "t_mapping(t_uint256,t_struct(TopBid)6182_storage)",
            "contract": "DeciblingAuctionV2",
            "src": "contracts/DeciblingAuctionV2.sol:49"
          }
        ],
        "types": {
          "t_address": {
            "label": "address",
            "numberOfBytes": "20"
          },
          "t_array(t_uint256)49_storage": {
            "label": "uint256[49]",
            "numberOfBytes": "1568"
          },
          "t_array(t_uint256)50_storage": {
            "label": "uint256[50]",
            "numberOfBytes": "1600"
          },
          "t_bool": {
            "label": "bool",
            "numberOfBytes": "1"
          },
          "t_contract(DeciblingNFTV2)7549": {
            "label": "contract DeciblingNFTV2",
            "numberOfBytes": "20"
          },
          "t_contract(IERC20)4886": {
            "label": "contract IERC20",
            "numberOfBytes": "20"
          },
          "t_mapping(t_uint256,t_struct(Auction)6195_storage)": {
            "label": "mapping(uint256 => struct DeciblingAuctionV2.Auction)",
            "numberOfBytes": "32"
          },
          "t_mapping(t_uint256,t_struct(NftAuctionInfo)6202_storage)": {
            "label": "mapping(uint256 => struct DeciblingAuctionV2.NftAuctionInfo)",
            "numberOfBytes": "32"
          },
          "t_mapping(t_uint256,t_struct(TopBid)6182_storage)": {
            "label": "mapping(uint256 => struct DeciblingAuctionV2.TopBid)",
            "numberOfBytes": "32"
          },
          "t_struct(Auction)6195_storage": {
            "label": "struct DeciblingAuctionV2.Auction",
            "members": [
              {
                "label": "winner",
                "type": "t_address",
                "offset": 0,
                "slot": "0"
              },
              {
                "label": "startPrice",
                "type": "t_uint256",
                "offset": 0,
                "slot": "1"
              },
              {
                "label": "increment",
                "type": "t_uint256",
                "offset": 0,
                "slot": "2"
              },
              {
                "label": "startTime",
                "type": "t_uint256",
                "offset": 0,
                "slot": "3"
              },
              {
                "label": "endTime",
                "type": "t_uint256",
                "offset": 0,
                "slot": "4"
              },
              {
                "label": "resulted",
                "type": "t_bool",
                "offset": 0,
                "slot": "5"
              }
            ],
            "numberOfBytes": "192"
          },
          "t_struct(NftAuctionInfo)6202_storage": {
            "label": "struct DeciblingAuctionV2.NftAuctionInfo",
            "members": [
              {
                "label": "price",
                "type": "t_uint256",
                "offset": 0,
                "slot": "0"
              },
              {
                "label": "saleCount",
                "type": "t_uint256",
                "offset": 0,
                "slot": "1"
              },
              {
                "label": "isBidding",
                "type": "t_bool",
                "offset": 0,
                "slot": "2"
              }
            ],
            "numberOfBytes": "96"
          },
          "t_struct(TopBid)6182_storage": {
            "label": "struct DeciblingAuctionV2.TopBid",
            "members": [
              {
                "label": "user",
                "type": "t_address",
                "offset": 0,
                "slot": "0"
              },
              {
                "label": "price",
                "type": "t_uint256",
                "offset": 0,
                "slot": "1"
              }
            ],
            "numberOfBytes": "64"
          },
          "t_uint256": {
            "label": "uint256",
            "numberOfBytes": "32"
          },
          "t_uint8": {
            "label": "uint8",
            "numberOfBytes": "1"
          }
        }
      }
    },
    "8280687a3e5b6b7c4c0b705960cd1ca0fabd535b98c99f47d5b1ae0f3f34f5d2": {
      "address": "0x786C7164A2Ad7B7caF5aA5f3634a68A65a77C6aE",
      "txHash": "0x852a85aeaea5642cea9e409e2829ddd6081cf96bc8f1c29186ae72a45442948f",
      "layout": {
        "solcVersion": "0.8.9",
        "storage": [
          {
            "label": "_initialized",
            "offset": 0,
            "slot": "0",
            "type": "t_uint8",
            "contract": "Initializable",
            "src": "@openzeppelin/contracts-upgradeable/proxy/utils/Initializable.sol:62",
            "retypedFrom": "bool"
          },
          {
            "label": "_initializing",
            "offset": 1,
            "slot": "0",
            "type": "t_bool",
            "contract": "Initializable",
            "src": "@openzeppelin/contracts-upgradeable/proxy/utils/Initializable.sol:67"
          },
          {
            "label": "_status",
            "offset": 0,
            "slot": "1",
            "type": "t_uint256",
            "contract": "ReentrancyGuardUpgradeable",
            "src": "@openzeppelin/contracts-upgradeable/security/ReentrancyGuardUpgradeable.sol:38"
          },
          {
            "label": "__gap",
            "offset": 0,
            "slot": "2",
            "type": "t_array(t_uint256)49_storage",
            "contract": "ReentrancyGuardUpgradeable",
            "src": "@openzeppelin/contracts-upgradeable/security/ReentrancyGuardUpgradeable.sol:80"
          },
          {
            "label": "__gap",
            "offset": 0,
            "slot": "51",
            "type": "t_array(t_uint256)50_storage",
            "contract": "ContextUpgradeable",
            "src": "@openzeppelin/contracts-upgradeable/utils/ContextUpgradeable.sol:36"
          },
          {
            "label": "_owner",
            "offset": 0,
            "slot": "101",
            "type": "t_address",
            "contract": "OwnableUpgradeable",
            "src": "@openzeppelin/contracts-upgradeable/access/OwnableUpgradeable.sol:22"
          },
          {
            "label": "__gap",
            "offset": 0,
            "slot": "102",
            "type": "t_array(t_uint256)49_storage",
            "contract": "OwnableUpgradeable",
            "src": "@openzeppelin/contracts-upgradeable/access/OwnableUpgradeable.sol:94"
          },
          {
            "label": "__gap",
            "offset": 0,
            "slot": "151",
            "type": "t_array(t_uint256)50_storage",
            "contract": "ERC1967UpgradeUpgradeable",
            "src": "@openzeppelin/contracts-upgradeable/proxy/ERC1967/ERC1967UpgradeUpgradeable.sol:197"
          },
          {
            "label": "__gap",
            "offset": 0,
            "slot": "201",
            "type": "t_array(t_uint256)50_storage",
            "contract": "UUPSUpgradeable",
            "src": "@openzeppelin/contracts-upgradeable/proxy/utils/UUPSUpgradeable.sol:107"
          },
          {
            "label": "token",
            "offset": 0,
            "slot": "251",
            "type": "t_contract(IERC20)4299",
            "contract": "DeciblingAuctionV2",
            "src": "contracts/DeciblingAuctionV2.sol:18"
          },
          {
            "label": "nftContract",
            "offset": 0,
            "slot": "252",
            "type": "t_contract(DeciblingNFTV2)6759",
            "contract": "DeciblingAuctionV2",
            "src": "contracts/DeciblingAuctionV2.sol:19"
          },
          {
            "label": "firstSaleFee",
            "offset": 0,
            "slot": "253",
            "type": "t_uint256",
            "contract": "DeciblingAuctionV2",
            "src": "contracts/DeciblingAuctionV2.sol:22"
          },
          {
            "label": "secondSaleFee",
            "offset": 0,
            "slot": "254",
            "type": "t_uint256",
            "contract": "DeciblingAuctionV2",
            "src": "contracts/DeciblingAuctionV2.sol:23"
          },
          {
            "label": "platformFeeRecipient",
            "offset": 0,
            "slot": "255",
            "type": "t_address",
            "contract": "DeciblingAuctionV2",
            "src": "contracts/DeciblingAuctionV2.sol:25"
          },
          {
            "label": "nftAuctionInfos",
            "offset": 0,
            "slot": "256",
            "type": "t_mapping(t_uint256,t_struct(NftAuctionInfo)5568_storage)",
            "contract": "DeciblingAuctionV2",
            "src": "contracts/DeciblingAuctionV2.sol:47"
          },
          {
            "label": "auctions",
            "offset": 0,
            "slot": "257",
            "type": "t_mapping(t_uint256,t_struct(Auction)5561_storage)",
            "contract": "DeciblingAuctionV2",
            "src": "contracts/DeciblingAuctionV2.sol:48"
          },
          {
            "label": "topBids",
            "offset": 0,
            "slot": "258",
            "type": "t_mapping(t_uint256,t_struct(TopBid)5548_storage)",
            "contract": "DeciblingAuctionV2",
            "src": "contracts/DeciblingAuctionV2.sol:49"
          }
        ],
        "types": {
          "t_address": {
            "label": "address",
            "numberOfBytes": "20"
          },
          "t_array(t_uint256)49_storage": {
            "label": "uint256[49]",
            "numberOfBytes": "1568"
          },
          "t_array(t_uint256)50_storage": {
            "label": "uint256[50]",
            "numberOfBytes": "1600"
          },
          "t_bool": {
            "label": "bool",
            "numberOfBytes": "1"
          },
          "t_contract(DeciblingNFTV2)6759": {
            "label": "contract DeciblingNFTV2",
            "numberOfBytes": "20"
          },
          "t_contract(IERC20)4299": {
            "label": "contract IERC20",
            "numberOfBytes": "20"
          },
          "t_mapping(t_uint256,t_struct(Auction)5561_storage)": {
            "label": "mapping(uint256 => struct DeciblingAuctionV2.Auction)",
            "numberOfBytes": "32"
          },
          "t_mapping(t_uint256,t_struct(NftAuctionInfo)5568_storage)": {
            "label": "mapping(uint256 => struct DeciblingAuctionV2.NftAuctionInfo)",
            "numberOfBytes": "32"
          },
          "t_mapping(t_uint256,t_struct(TopBid)5548_storage)": {
            "label": "mapping(uint256 => struct DeciblingAuctionV2.TopBid)",
            "numberOfBytes": "32"
          },
          "t_struct(Auction)5561_storage": {
            "label": "struct DeciblingAuctionV2.Auction",
            "members": [
              {
                "label": "winner",
                "type": "t_address",
                "offset": 0,
                "slot": "0"
              },
              {
                "label": "startPrice",
                "type": "t_uint256",
                "offset": 0,
                "slot": "1"
              },
              {
                "label": "increment",
                "type": "t_uint256",
                "offset": 0,
                "slot": "2"
              },
              {
                "label": "startTime",
                "type": "t_uint256",
                "offset": 0,
                "slot": "3"
              },
              {
                "label": "endTime",
                "type": "t_uint256",
                "offset": 0,
                "slot": "4"
              },
              {
                "label": "resulted",
                "type": "t_bool",
                "offset": 0,
                "slot": "5"
              }
            ],
            "numberOfBytes": "192"
          },
          "t_struct(NftAuctionInfo)5568_storage": {
            "label": "struct DeciblingAuctionV2.NftAuctionInfo",
            "members": [
              {
                "label": "price",
                "type": "t_uint256",
                "offset": 0,
                "slot": "0"
              },
              {
                "label": "saleCount",
                "type": "t_uint256",
                "offset": 0,
                "slot": "1"
              },
              {
                "label": "isBidding",
                "type": "t_bool",
                "offset": 0,
                "slot": "2"
              }
            ],
            "numberOfBytes": "96"
          },
          "t_struct(TopBid)5548_storage": {
            "label": "struct DeciblingAuctionV2.TopBid",
            "members": [
              {
                "label": "user",
                "type": "t_address",
                "offset": 0,
                "slot": "0"
              },
              {
                "label": "price",
                "type": "t_uint256",
                "offset": 0,
                "slot": "1"
              }
            ],
            "numberOfBytes": "64"
          },
          "t_uint256": {
            "label": "uint256",
            "numberOfBytes": "32"
          },
          "t_uint8": {
            "label": "uint8",
            "numberOfBytes": "1"
          }
        }
      }
    },
    "fdf33fe2dbf9c2dd6be264632ac76e02f9d6bd2fa37a9f53f4e494bea606bf27": {
      "address": "0x97766536605af7579415a50F2D54d81522B07bc4",
      "layout": {
        "solcVersion": "0.8.9",
        "storage": [
          {
            "label": "_initialized",
            "offset": 0,
            "slot": "0",
            "type": "t_uint8",
            "contract": "Initializable",
            "src": "@openzeppelin/contracts-upgradeable/proxy/utils/Initializable.sol:62",
            "retypedFrom": "bool"
          },
          {
            "label": "_initializing",
            "offset": 1,
            "slot": "0",
            "type": "t_bool",
            "contract": "Initializable",
            "src": "@openzeppelin/contracts-upgradeable/proxy/utils/Initializable.sol:67"
          },
          {
            "label": "__gap",
            "offset": 0,
            "slot": "1",
            "type": "t_array(t_uint256)50_storage",
            "contract": "ContextUpgradeable",
            "src": "@openzeppelin/contracts-upgradeable/utils/ContextUpgradeable.sol:36"
          },
          {
            "label": "_owner",
            "offset": 0,
            "slot": "51",
            "type": "t_address",
            "contract": "OwnableUpgradeable",
            "src": "@openzeppelin/contracts-upgradeable/access/OwnableUpgradeable.sol:22"
          },
          {
            "label": "__gap",
            "offset": 0,
            "slot": "52",
            "type": "t_array(t_uint256)49_storage",
            "contract": "OwnableUpgradeable",
            "src": "@openzeppelin/contracts-upgradeable/access/OwnableUpgradeable.sol:94"
          },
          {
            "label": "_status",
            "offset": 0,
            "slot": "101",
            "type": "t_uint256",
            "contract": "ReentrancyGuardUpgradeable",
            "src": "@openzeppelin/contracts-upgradeable/security/ReentrancyGuardUpgradeable.sol:38"
          },
          {
            "label": "__gap",
            "offset": 0,
            "slot": "102",
            "type": "t_array(t_uint256)49_storage",
            "contract": "ReentrancyGuardUpgradeable",
            "src": "@openzeppelin/contracts-upgradeable/security/ReentrancyGuardUpgradeable.sol:80"
          },
          {
            "label": "__gap",
            "offset": 0,
            "slot": "151",
            "type": "t_array(t_uint256)50_storage",
            "contract": "ERC1967UpgradeUpgradeable",
            "src": "@openzeppelin/contracts-upgradeable/proxy/ERC1967/ERC1967UpgradeUpgradeable.sol:211"
          },
          {
            "label": "__gap",
            "offset": 0,
            "slot": "201",
            "type": "t_array(t_uint256)50_storage",
            "contract": "UUPSUpgradeable",
            "src": "@openzeppelin/contracts-upgradeable/proxy/utils/UUPSUpgradeable.sol:107"
          },
          {
            "label": "token",
            "offset": 0,
            "slot": "251",
            "type": "t_contract(IERC20)2904",
            "contract": "DeciblingStaking",
            "src": "contracts/DeciblingStaking.sol:26"
          },
          {
            "label": "treasury",
            "offset": 0,
            "slot": "252",
            "type": "t_contract(DeciblingReserve)3230",
            "contract": "DeciblingStaking",
            "src": "contracts/DeciblingStaking.sol:27"
          },
          {
            "label": "merkleRoot",
            "offset": 0,
            "slot": "253",
            "type": "t_bytes32",
            "contract": "DeciblingStaking",
            "src": "contracts/DeciblingStaking.sol:28"
          },
          {
            "label": "stakers",
            "offset": 0,
            "slot": "254",
            "type": "t_mapping(t_string_memory_ptr,t_mapping(t_address,t_struct(StakeInfo)3281_storage))",
            "contract": "DeciblingStaking",
            "src": "contracts/DeciblingStaking.sol:45"
          },
          {
            "label": "pools",
            "offset": 0,
            "slot": "255",
            "type": "t_mapping(t_string_memory_ptr,t_struct(PoolInfo)3294_storage)",
            "contract": "DeciblingStaking",
            "src": "contracts/DeciblingStaking.sol:46"
          }
        ],
        "types": {
          "t_address": {
            "label": "address",
            "numberOfBytes": "20"
          },
          "t_array(t_uint256)49_storage": {
            "label": "uint256[49]",
            "numberOfBytes": "1568"
          },
          "t_array(t_uint256)50_storage": {
            "label": "uint256[50]",
            "numberOfBytes": "1600"
          },
          "t_bool": {
            "label": "bool",
            "numberOfBytes": "1"
          },
          "t_bytes32": {
            "label": "bytes32",
            "numberOfBytes": "32"
          },
          "t_contract(DeciblingReserve)3230": {
            "label": "contract DeciblingReserve",
            "numberOfBytes": "20"
          },
          "t_contract(IERC20)2904": {
            "label": "contract IERC20",
            "numberOfBytes": "20"
          },
          "t_mapping(t_address,t_struct(StakeInfo)3281_storage)": {
            "label": "mapping(address => struct DeciblingStaking.StakeInfo)",
            "numberOfBytes": "32"
          },
          "t_mapping(t_string_memory_ptr,t_mapping(t_address,t_struct(StakeInfo)3281_storage))": {
            "label": "mapping(string => mapping(address => struct DeciblingStaking.StakeInfo))",
            "numberOfBytes": "32"
          },
          "t_mapping(t_string_memory_ptr,t_struct(PoolInfo)3294_storage)": {
            "label": "mapping(string => struct DeciblingStaking.PoolInfo)",
            "numberOfBytes": "32"
          },
          "t_string_memory_ptr": {
            "label": "string",
            "numberOfBytes": "32"
          },
          "t_struct(PoolInfo)3294_storage": {
            "label": "struct DeciblingStaking.PoolInfo",
            "members": [
              {
                "label": "owner",
                "type": "t_address",
                "offset": 0,
                "slot": "0"
              },
              {
                "label": "hardCap",
                "type": "t_uint256",
                "offset": 0,
                "slot": "1"
              },
              {
                "label": "totalDeposit",
                "type": "t_uint256",
                "offset": 0,
                "slot": "2"
              },
              {
                "label": "rToOwner",
                "type": "t_uint8",
                "offset": 0,
                "slot": "3"
              },
              {
                "label": "r",
                "type": "t_uint8",
                "offset": 1,
                "slot": "3"
              },
              {
                "label": "isDefault",
                "type": "t_bool",
                "offset": 2,
                "slot": "3"
              }
            ],
            "numberOfBytes": "128"
          },
          "t_struct(StakeInfo)3281_storage": {
            "label": "struct DeciblingStaking.StakeInfo",
            "members": [
              {
                "label": "totalDeposit",
                "type": "t_uint256",
                "offset": 0,
                "slot": "0"
              },
              {
                "label": "depositTime",
                "type": "t_uint256",
                "offset": 0,
                "slot": "1"
              },
              {
                "label": "lastPayout",
                "type": "t_uint256",
                "offset": 0,
                "slot": "2"
              },
              {
                "label": "lastPayoutToPoolOwner",
                "type": "t_uint256",
                "offset": 0,
                "slot": "3"
              }
            ],
            "numberOfBytes": "128"
          },
          "t_uint256": {
            "label": "uint256",
            "numberOfBytes": "32"
          },
          "t_uint8": {
            "label": "uint8",
            "numberOfBytes": "1"
          },
          "t_string_storage": {
            "label": "string"
          }
        }
      }
    },
    "cecb6409662b747065cdff578c753a5d22d9d4b3a256b3b903785145ec1a5e78": {
      "address": "0x40C4d72291F4D1F0F46c48f656a350685BB18450",
      "txHash": "0x0514bde98fe5092969e069f311561bd4a560641263ad39c14cb6096854c8df27",
      "layout": {
        "solcVersion": "0.8.9",
        "storage": [
          {
            "label": "_initialized",
            "offset": 0,
            "slot": "0",
            "type": "t_uint8",
            "contract": "Initializable",
            "src": "@openzeppelin/contracts-upgradeable/proxy/utils/Initializable.sol:62",
            "retypedFrom": "bool"
          },
          {
            "label": "_initializing",
            "offset": 1,
            "slot": "0",
            "type": "t_bool",
            "contract": "Initializable",
            "src": "@openzeppelin/contracts-upgradeable/proxy/utils/Initializable.sol:67"
          },
          {
            "label": "__gap",
            "offset": 0,
            "slot": "1",
            "type": "t_array(t_uint256)50_storage",
            "contract": "ContextUpgradeable",
            "src": "@openzeppelin/contracts-upgradeable/utils/ContextUpgradeable.sol:36"
          },
          {
            "label": "_owner",
            "offset": 0,
            "slot": "51",
            "type": "t_address",
            "contract": "OwnableUpgradeable",
            "src": "@openzeppelin/contracts-upgradeable/access/OwnableUpgradeable.sol:22"
          },
          {
            "label": "__gap",
            "offset": 0,
            "slot": "52",
            "type": "t_array(t_uint256)49_storage",
            "contract": "OwnableUpgradeable",
            "src": "@openzeppelin/contracts-upgradeable/access/OwnableUpgradeable.sol:94"
          },
          {
            "label": "_status",
            "offset": 0,
            "slot": "101",
            "type": "t_uint256",
            "contract": "ReentrancyGuardUpgradeable",
            "src": "@openzeppelin/contracts-upgradeable/security/ReentrancyGuardUpgradeable.sol:38"
          },
          {
            "label": "__gap",
            "offset": 0,
            "slot": "102",
            "type": "t_array(t_uint256)49_storage",
            "contract": "ReentrancyGuardUpgradeable",
            "src": "@openzeppelin/contracts-upgradeable/security/ReentrancyGuardUpgradeable.sol:80"
          },
          {
            "label": "__gap",
            "offset": 0,
            "slot": "151",
            "type": "t_array(t_uint256)50_storage",
            "contract": "ERC1967UpgradeUpgradeable",
            "src": "@openzeppelin/contracts-upgradeable/proxy/ERC1967/ERC1967UpgradeUpgradeable.sol:211"
          },
          {
            "label": "__gap",
            "offset": 0,
            "slot": "201",
            "type": "t_array(t_uint256)50_storage",
            "contract": "UUPSUpgradeable",
            "src": "@openzeppelin/contracts-upgradeable/proxy/utils/UUPSUpgradeable.sol:107"
          },
          {
            "label": "token",
            "offset": 0,
            "slot": "251",
            "type": "t_contract(IERC20)2904",
            "contract": "DeciblingStaking",
            "src": "contracts/DeciblingStaking.sol:26"
          },
          {
            "label": "treasury",
            "offset": 0,
            "slot": "252",
            "type": "t_contract(DeciblingReserve)3230",
            "contract": "DeciblingStaking",
            "src": "contracts/DeciblingStaking.sol:27"
          },
          {
            "label": "merkleRoot",
            "offset": 0,
            "slot": "253",
            "type": "t_bytes32",
            "contract": "DeciblingStaking",
            "src": "contracts/DeciblingStaking.sol:28"
          },
          {
            "label": "stakers",
            "offset": 0,
            "slot": "254",
            "type": "t_mapping(t_string_memory_ptr,t_mapping(t_address,t_struct(StakeInfo)3281_storage))",
            "contract": "DeciblingStaking",
            "src": "contracts/DeciblingStaking.sol:45"
          },
          {
            "label": "pools",
            "offset": 0,
            "slot": "255",
            "type": "t_mapping(t_string_memory_ptr,t_struct(PoolInfo)3294_storage)",
            "contract": "DeciblingStaking",
            "src": "contracts/DeciblingStaking.sol:46"
          }
        ],
        "types": {
          "t_address": {
            "label": "address",
            "numberOfBytes": "20"
          },
          "t_array(t_uint256)49_storage": {
            "label": "uint256[49]",
            "numberOfBytes": "1568"
          },
          "t_array(t_uint256)50_storage": {
            "label": "uint256[50]",
            "numberOfBytes": "1600"
          },
          "t_bool": {
            "label": "bool",
            "numberOfBytes": "1"
          },
          "t_bytes32": {
            "label": "bytes32",
            "numberOfBytes": "32"
          },
          "t_contract(DeciblingReserve)3230": {
            "label": "contract DeciblingReserve",
            "numberOfBytes": "20"
          },
          "t_contract(IERC20)2904": {
            "label": "contract IERC20",
            "numberOfBytes": "20"
          },
          "t_mapping(t_address,t_struct(StakeInfo)3281_storage)": {
            "label": "mapping(address => struct DeciblingStaking.StakeInfo)",
            "numberOfBytes": "32"
          },
          "t_mapping(t_string_memory_ptr,t_mapping(t_address,t_struct(StakeInfo)3281_storage))": {
            "label": "mapping(string => mapping(address => struct DeciblingStaking.StakeInfo))",
            "numberOfBytes": "32"
          },
          "t_mapping(t_string_memory_ptr,t_struct(PoolInfo)3294_storage)": {
            "label": "mapping(string => struct DeciblingStaking.PoolInfo)",
            "numberOfBytes": "32"
          },
          "t_string_memory_ptr": {
            "label": "string",
            "numberOfBytes": "32"
          },
          "t_struct(PoolInfo)3294_storage": {
            "label": "struct DeciblingStaking.PoolInfo",
            "members": [
              {
                "label": "owner",
                "type": "t_address",
                "offset": 0,
                "slot": "0"
              },
              {
                "label": "hardCap",
                "type": "t_uint256",
                "offset": 0,
                "slot": "1"
              },
              {
                "label": "totalDeposit",
                "type": "t_uint256",
                "offset": 0,
                "slot": "2"
              },
              {
                "label": "rToOwner",
                "type": "t_uint8",
                "offset": 0,
                "slot": "3"
              },
              {
                "label": "r",
                "type": "t_uint8",
                "offset": 1,
                "slot": "3"
              },
              {
                "label": "isDefault",
                "type": "t_bool",
                "offset": 2,
                "slot": "3"
              }
            ],
            "numberOfBytes": "128"
          },
          "t_struct(StakeInfo)3281_storage": {
            "label": "struct DeciblingStaking.StakeInfo",
            "members": [
              {
                "label": "totalDeposit",
                "type": "t_uint256",
                "offset": 0,
                "slot": "0"
              },
              {
                "label": "depositTime",
                "type": "t_uint256",
                "offset": 0,
                "slot": "1"
              },
              {
                "label": "lastPayout",
                "type": "t_uint256",
                "offset": 0,
                "slot": "2"
              },
              {
                "label": "lastPayoutToPoolOwner",
                "type": "t_uint256",
                "offset": 0,
                "slot": "3"
              }
            ],
            "numberOfBytes": "128"
          },
          "t_uint256": {
            "label": "uint256",
            "numberOfBytes": "32"
          },
          "t_uint8": {
            "label": "uint8",
            "numberOfBytes": "1"
          },
          "t_string_storage": {
            "label": "string"
          }
        }
      }
    }
  }
}
